DIYA_Voice/__init__.py
DIYA_Voice/core.py
DIYA_Voice/utils.py
diya_voice-0.15.0.dist-info/METADATA
diya_voice-0.15.0.dist-info/WHEEL
diya_voice-0.15.0.dist-info/top_level.txt
diya_voice-0.15.0.dist-info/RECORD
