Metadata-Version: 2.4
Name: DIYA_Voice
Version: 0.15.0
Summary: Offline Voice-Controlled LED and Robotics GUI for ESP32 using Vosk.
Home-page: https://github.com/yourusername/DIYA_Voice
Author: DIYA Robotics
Author-email: learn@diyaedulabs.com
Classifier: Programming Language :: Python :: 3
Classifier: Operating System :: Microsoft :: Windows
Classifier: Intended Audience :: Education
Classifier: Topic :: Education
Classifier: Topic :: Scientific/Engineering :: Artificial Intelligence
Classifier: Topic :: Software Development :: Libraries :: Python Modules
Requires-Python: >=3.7
Requires-Dist: vosk==0.3.45
Requires-Dist: sounddevice>=0.5.2
Requires-Dist: numpy>=1.20.0
Requires-Dist: tqdm>=4.60.0
Requires-Dist: requests>=2.25.0
Requires-Dist: pyserial>=3.5
Dynamic: author
Dynamic: author-email
Dynamic: classifier
Dynamic: description
Dynamic: description-content-type
Dynamic: home-page
Dynamic: requires-dist
Dynamic: requires-python
Dynamic: summary
